{
  "contacts": [
    {
      "fullname": "علی امینی",
      "image": "https://i.pravatar.cc/150?img=8",
      "mobile": "09367449830",
      "email": "ali@gmail.com",
      "job": "مهندس عمران",
      "group": 1,
      "id": 2
    },
    {
      "fullname": "بختیار محمدی",
      "mobile": "09352273552",
      "email": "zmxn1212@hi2.in",
      "job": "دانشجو",
      "group": "2",
      "image": "https://i.pravatar.cc/150?img=13",
      "id": 5
    }
  ],
  "groups": [
    {
      "id": 1,
      "name": "همکار"
    },
    {
      "id": 2,
      "name": "دوست"
    },
    {
      "id": 3,
      "name": "فامیل"
    },
    {
      "id": 4,
      "name": "سرویس"
    },
    {
      "id": 5,
      "name": "آشنا"
    }
  ]
}